klisch/__init__.py
klisch/command.py
klisch/config.py
klisch/deploy.py
klisch/env.py
klisch/files.py
klisch/logger.py
klisch/utils.py
test/__init__.py
test/test_command.py
klisch-0.6.0.dist-info/LICENSE
klisch-0.6.0.dist-info/METADATA
klisch-0.6.0.dist-info/WHEEL
klisch-0.6.0.dist-info/top_level.txt
klisch-0.6.0.dist-info/RECORD
