Metadata-Version: 2.1
Name: klisch
Version: 0.6.0
Summary: A cli-integrate config system
Home-page: https://github.com/leVirve/klisch
Author: leVirve Salas
Author-email: gae.m.project@gmail.com
License: UNKNOWN
Platform: UNKNOWN
Classifier: Programming Language :: Python :: 3
Classifier: License :: OSI Approved :: MIT License
Classifier: Operating System :: OS Independent
Requires-Dist: yacs
